certwatch/__init__.py
certwatch/library.py
certwatch/main.py
pnu_certwatch-1.0.3.data/data/share/certwatch/tests.txt
pnu_certwatch-1.0.3.data/data/share/man/man1/certwatch.1.gz
pnu_certwatch-1.0.3.dist-info/License
pnu_certwatch-1.0.3.dist-info/METADATA
pnu_certwatch-1.0.3.dist-info/WHEEL
pnu_certwatch-1.0.3.dist-info/entry_points.txt
pnu_certwatch-1.0.3.dist-info/top_level.txt
pnu_certwatch-1.0.3.dist-info/RECORD
