Metadata-Version: 2.1
Name: pnu-certwatch
Version: 1.0.3
Summary: watch X509 certificates expiration dates
Home-page: https://github.com/HubTou/certwatch/
Author: Hubert Tournier
Author-email: hubert.tournier@gmail.com
License: BSD 3-Clause License
Project-URL: Bug Tracker, https://github.com/HubTou/certwatch/issues
Keywords: pnu-project
Classifier: Development Status :: 5 - Production/Stable
Classifier: Environment :: Console
Classifier: Intended Audience :: System Administrators
Classifier: Intended Audience :: Information Technology
Classifier: License :: OSI Approved :: BSD License
Classifier: Natural Language :: English
Classifier: Operating System :: OS Independent
Classifier: Operating System :: POSIX :: BSD :: FreeBSD
Classifier: Operating System :: Microsoft :: Windows
Classifier: Programming Language :: Python :: 3.6
Classifier: Programming Language :: Python :: 3.7
Classifier: Programming Language :: Python :: 3.8
Classifier: Programming Language :: Python :: 3.9
Classifier: Programming Language :: Python :: 3.10
Classifier: Programming Language :: Python :: 3.11
Classifier: Programming Language :: Python :: 3.12
Classifier: Topic :: Utilities
Classifier: Topic :: File Formats
Classifier: Topic :: Internet
Classifier: Topic :: Security
Classifier: Topic :: Security :: Cryptography
Classifier: Topic :: System :: Monitoring
Requires-Python: >=3.6
License-File: License
Requires-Dist: pnu-libpnu
Requires-Dist: cryptography
Requires-Dist: openpyxl
Requires-Dist: prettytable
Requires-Dist: tqdm
